bfms/__init__.py
bfms/py.typed
bfms/ml/__init__.py
bfms/ml/kmeans.py
bfms/nn/__init__.py
bfms/nn/attentions/__init__.py
bfms/nn/attentions/criss_cross_attention.py
bfms/nn/attentions/neural_transformer_attention.py
bfms/nn/embeddings/__init__.py
bfms/nn/embeddings/spatial_embedding.py
bfms/nn/embeddings/temporal_embedding.py
bfms/nn/functional/__init__.py
bfms/nn/functional/norm.py
bfms/nn/quantizers/__init__.py
bfms/nn/quantizers/norm_ema_quantizer.py
bfms/utils/__init__.py
bfms/utils/sampling.py
bfms/utils/weights.py
bfms-0.1.1.dist-info/METADATA
bfms-0.1.1.dist-info/WHEEL
bfms-0.1.1.dist-info/licenses/LICENSE
bfms-0.1.1.dist-info/RECORD
