Metadata-Version: 2.4
Name: bfms
Version: 0.1.1
Summary: Brain Foundation Models
Author-email: Prannaya Gupta <prannayagupta@gmail.com>
License-File: LICENSE
Requires-Python: >=3.10
Requires-Dist: einops~=0.6.0
Requires-Dist: torch~=2.0
